docs/source/conf.py
tree_to_script/__init__.py
tree_to_script/command_generator.py
tree_to_script/debug.py
tree_to_script/main.py
tree_to_script/models.py
tree_to_script/py.typed
tree_to_script/serializers.py
tree_to_script/test_integration.py
tree_to_script/test_tree_parser.py
tree_to_script/tree_parser.py
tree_to_script-0.1.2.dist-info/METADATA
tree_to_script-0.1.2.dist-info/WHEEL
tree_to_script-0.1.2.dist-info/top_level.txt
tree_to_script-0.1.2.dist-info/RECORD
