Metadata-Version: 2.2
Name: tree-to-script
Version: 0.1.2
Summary: A utility for transforming directory tree structures from text into actionable shell commands or executing them directly
Author-email: vanuan <vanuan+tree-to-script@gmail.com>
Project-URL: Homepage, https://github.com/vanuan/tree-to-script
Project-URL: Bug Tracker, https://github.com/vanuan/tree-to-script/issues
Project-URL: Documentation, https://vanuan.github.io/tree-to-script
Classifier: Programming Language :: Python :: 3
Classifier: License :: OSI Approved :: MIT License
Classifier: Operating System :: OS Independent
Requires-Python: >=3.7
